alqtendpy/__init__.py
alqtendpy/_version.py
alqtendpy/asyncio.py
alqtendpy/attrs.py
alqtendpy/compileui.py
alqtendpy/core.py
alqtendpy/models.py
alqtendpy/twisted.py
alqtendpy/cli/__init__.py
alqtendpy/cli/compileui.py
alqtendpy/tests/__init__.py
alqtendpy/tests/test_asyncio.py
alqtendpy/tests/test_attrs.py
alqtendpy/tests/test_core.py
alqtendpy/tests/test_twisted.py
alqtendpy/tests/utils.py
alqtendpy-0.1.1.dist-info/METADATA
alqtendpy-0.1.1.dist-info/WHEEL
alqtendpy-0.1.1.dist-info/entry_points.txt
alqtendpy-0.1.1.dist-info/top_level.txt
alqtendpy-0.1.1.dist-info/RECORD
