Metadata-Version: 2.1
Name: alqtendpy
Version: 0.1.1
Summary: Extras for working with PyQt5.
Home-page: https://github.com/altendky/alqtendpy
Author: Kyle Altendorf
Author-email: sda@fstab.net
License: UNKNOWN
Platform: UNKNOWN
Classifier: Development Status :: 3 - Alpha
Classifier: Intended Audience :: Developers
Classifier: Programming Language :: Python :: 3
Classifier: Programming Language :: Python :: 3.5
Classifier: Programming Language :: Python :: 3.6
Requires-Dist: altendpy
Requires-Dist: click
Requires-Dist: attrs
Requires-Dist: pyqt5
Provides-Extra: dev
Requires-Dist: gitignoreio ; extra == 'dev'
Provides-Extra: test
Requires-Dist: codecov ; extra == 'test'
Requires-Dist: pytest ; extra == 'test'
Requires-Dist: pytest-cov ; extra == 'test'
Requires-Dist: pytest-qt ; extra == 'test'
Requires-Dist: pytest-twisted ; extra == 'test'
Requires-Dist: pytest-xvfb ; extra == 'test'
Requires-Dist: quamash ; extra == 'test'
Requires-Dist: qt5reactor ; extra == 'test'
Requires-Dist: tox ; extra == 'test'
Requires-Dist: twisted ; extra == 'test'
Requires-Dist: twisted[windows_platform] ; (sys_platform == "win32") and extra == 'test'
